shuttl_geo/__init__.py
shuttl_geo/distance.py
shuttl_geo/location.py
tests/__init__.py
tests/test_distance.py
tests/test_location.py
shuttl_geo-0.0.3.dist-info/METADATA
shuttl_geo-0.0.3.dist-info/WHEEL
shuttl_geo-0.0.3.dist-info/top_level.txt
shuttl_geo-0.0.3.dist-info/RECORD
