Metadata-Version: 2.1
Name: shuttl-geo
Version: 0.0.3
Summary: Geographic helpers
Home-page: UNKNOWN
Author: Sherub Thakur
Author-email: sherub.thakur@shuttl.com
License: MIT
Platform: UNKNOWN
Classifier: Programming Language :: Python :: 3.7
Requires-Dist: shapely
Requires-Dist: geopy
Provides-Extra: dev
Requires-Dist: flake8 ; extra == 'dev'
Provides-Extra: test
Requires-Dist: pytest ; extra == 'test'
Requires-Dist: pytest-runner ; extra == 'test'
Requires-Dist: pytest-cov ; extra == 'test'
Requires-Dist: pytest-pep8 ; extra == 'test'
